circuit.v
`timescale 1ns / 1ps
`include "iob_lib.vh"

module circuit
  #(
    parameter W=0
    )
  (
   `INPUT(rst,1),
   `INPUT(clk,1),
   `INPUT(en,1),
   `INPUT(x,32),
   `OUTPUT(y,W)
   );

   `SIGNAL(cnt, 7) //7-bit counter as iterator
   
   `SIGNAL(y_int, W) //internal y
   `SIGNAL(y_int_n_1, W) //y(n-1)
   `SIGNAL(y_int_n_2, W) //y(n-2)
   `SIGNAL(y_final, W) //y_resultado
   `SIGNAL2OUT(y, y_final) //connect internal y to output

   //y shift register 
   `REG_ARE(clk, rst, 1'b0, cnt!=99, y_int_n_1, y_int)
   `REG_ARE(clk, rst, 1'b0, cnt!=99, y_int_n_2, x)

   //iteration counter
   `COUNTER_ARE(clk, rst, cnt!=99, cnt)

   //compute next why
   `COMB y_int = y_int_n_1 + y_int_n_2;

   `COMB y_final = y_int/100;
   
   
endmodule

circuit_tb.v
`timescale 1ns / 1ps
`include "iob_lib.vh"

`define W 98

module circuit_tb;

   `CLOCK(clk, 10)
   `RESET(rst, 1, 10)
   `SIGNAL(x, 32)
   `SIGNAL(en, 1)
   `SIGNAL_OUT(y, `W)

   integer i;
   
   initial begin
      $dumpfile("circuit.vcd");
      $dumpvars();
      en=0;
      x=0;
      for (i=0; i<100; i=i+1) begin
         @(posedge clk) #1 en=1; x=$urandom%1024;
      end

      $display("%d", y);
      @(posedge clk) #100 $finish;

   end 

   circuit
     #(
       .W(`W)
       ) 
   c0
     (
      .rst(rst),
      .clk(clk),
      .en(en),
      .x(x),
      .y(y)
      );


endmodule

circuit.vcd
$date
	Tue Nov 17 22:31:22 2020
$end
$version
	Icarus Verilog
$end
$timescale
	1ps
$end
$scope module circuit_tb $end
$var wire 98 ! y [97:0] $end
$var reg 1 " clk $end
$var reg 1 # en $end
$var reg 1 $ rst $end
$var reg 32 % x [31:0] $end
$var integer 32 & i [31:0] $end
$scope module c0 $end
$var wire 1 " clk $end
$var wire 1 # en $end
$var wire 1 $ rst $end
$var wire 32 ' x [31:0] $end
$var wire 98 ( y [97:0] $end
$var reg 7 ) cnt [6:0] $end
$var reg 98 * y_final [97:0] $end
$var reg 98 + y_int [97:0] $end
$var reg 98 , y_int_n_1 [97:0] $end
$var reg 98 - y_int_n_2 [97:0] $end
$upscope $end
$upscope $end
$enddefinitions $end
#0
$dumpvars
bx -
bx ,
bx +
bx *
bx )
bx (
b0 '
b0 &
b0 %
0$
0#
1"
bx !
$end
#1000
b0 !
b0 (
b0 *
b0 +
b0 )
b0 -
b0 ,
1$
#5000
0"
#10000
1"
#11000
b1 &
b100100100 %
b100100100 '
1#
0$
#15000
0"
#20000
b10 !
b10 (
b10 *
b100100100 +
b1 )
b100100100 -
1"
#21000
b10 &
b1010000001 %
b1010000001 '
#25000
0"
#30000
b1001 !
b1001 (
b1001 *
b1110100101 +
b100100100 ,
b1010000001 -
b10 )
1"
#31000
b11 &
b1000001001 %
b1000001001 '
#35000
0"
#40000
b1110 !
b1110 (
b1110 *
b10110101110 +
b11 )
b1000001001 -
b1110100101 ,
1"
#41000
b100 &
b1001100011 %
b1001100011 '
#45000
0"
#50000
b10100 !
b10100 (
b10100 *
b100000010001 +
b10110101110 ,
b1001100011 -
b100 )
1"
#51000
b101 &
b1100001101 %
b1100001101 '
#55000
0"
#60000
b11100 !
b11100 (
b11100 *
b101100011110 +
b101 )
b1100001101 -
b100000010001 ,
1"
#61000
b110 &
b110001101 %
b110001101 '
#65000
0"
#70000
b100000 !
b100000 (
b100000 *
b110010101011 +
b101100011110 ,
b110001101 -
b110 )
1"
#71000
b111 &
b1100101 %
b1100101 '
#75000
0"
#80000
b100001 !
b100001 (
b100001 *
b110100010000 +
b111 )
b1100101 -
b110010101011 ,
1"
#81000
b1000 &
b1000010010 %
b1000010010 '
#85000
0"
#90000
b100110 !
b100110 (
b100110 *
b111100100010 +
b110100010000 ,
b1000010010 -
b1000 )
1"
#91000
b1001 &
b1100000001 %
b1100000001 '
#95000
0"
#100000
b101110 !
b101110 (
b101110 *
b1001000100011 +
b1001 )
b1100000001 -
b111100100010 ,
1"
#101000
b1010 &
b100001101 %
b100001101 '
#105000
0"
#110000
b110001 !
b110001 (
b110001 *
b1001100110000 +
b1001000100011 ,
b100001101 -
b1010 )
1"
#111000
b1011 &
b101110110 %
b101110110 '
#115000
0"
#120000
b110100 !
b110100 (
b110100 *
b1010010100110 +
b1011 )
b101110110 -
b1001100110000 ,
1"
#121000
b1100 &
b100111101 %
b100111101 '
#125000
0"
#130000
b111000 !
b111000 (
b111000 *
b1010111100011 +
b1010010100110 ,
b100111101 -
b1100 )
1"
#131000
b1101 &
b1111101101 %
b1111101101 '
#135000
0"
#140000
b1000010 !
b1000010 (
b1000010 *
b1100111010000 +
b1101 )
b1111101101 -
b1010111100011 ,
1"
#141000
b1110 &
b1110001100 %
b1110001100 '
#145000
0"
#150000
b1001011 !
b1001011 (
b1001011 *
b1110101011100 +
b1100111010000 ,
b1110001100 -
b1110 )
1"
#151000
b1111 &
b111111001 %
b111111001 '
#155000
0"
#160000
b1010000 !
b1010000 (
b1010000 *
b1111101010101 +
b1111 )
b111111001 -
b1110101011100 ,
1"
#161000
b10000 &
b11000110 %
b11000110 '
#165000
0"
#170000
b1010010 !
b1010010 (
b1010010 *
b10000000011011 +
b1111101010101 ,
b11000110 -
b10000 )
1"
#171000
b10001 &
b11000101 %
b11000101 '
#175000
0"
#180000
b1010100 !
b1010100 (
b1010100 *
b10000011100000 +
b10001 )
b11000101 -
b10000000011011 ,
1"
#181000
b10010 &
b1010101010 %
b1010101010 '
#185000
0"
#190000
b1011010 !
b1011010 (
b1011010 *
b10001110001010 +
b10000011100000 ,
b1010101010 -
b10010 )
1"
#191000
b10011 &
b1111100101 %
b1111100101 '
#195000
0"
#200000
b1100100 !
b1100100 (
b1100100 *
b10011101101111 +
b10011 )
b1111100101 -
b10001110001010 ,
1"
#201000
b10100 &
b1001110111 %
b1001110111 '
#205000
0"
#210000
b1101011 !
b1101011 (
b1101011 *
b10100111100110 +
b10011101101111 ,
b1001110111 -
b10100 )
1"
#211000
b10101 &
b1000010010 %
b1000010010 '
#215000
0"
#220000
b1110000 !
b1110000 (
b1110000 *
b10101111111000 +
b10101 )
b1000010010 -
b10100111100110 ,
1"
#221000
b10110 &
b1110001111 %
b1110001111 '
#225000
0"
#230000
b1111001 !
b1111001 (
b1111001 *
b10111110000111 +
b10101111111000 ,
b1110001111 -
b10110 )
1"
#231000
b10111 &
b111110010 %
b111110010 '
#235000
0"
#240000
b1111110 !
b1111110 (
b1111110 *
b11000101111001 +
b10111 )
b111110010 -
b10111110000111 ,
1"
#241000
b11000 &
b1011001110 %
b1011001110 '
#245000
0"
#250000
b10000101 !
b10000101 (
b10000101 *
b11010001000111 +
b11000101111001 ,
b1011001110 -
b11000 )
1"
#251000
b11001 &
b1011101000 %
b1011101000 '
#255000
0"
#260000
b10001101 !
b10001101 (
b10001101 *
b11011100101111 +
b11001 )
b1011101000 -
b11010001000111 ,
1"
#261000
b11010 &
b1011000101 %
b1011000101 '
#265000
0"
#270000
b10010100 !
b10010100 (
b10010100 *
b11100111110100 +
b11011100101111 ,
b1011000101 -
b11010 )
1"
#271000
b11011 &
b101011100 %
b101011100 '
#275000
0"
#280000
b10010111 !
b10010111 (
b10010111 *
b11101101010000 +
b11011 )
b101011100 -
b11100111110100 ,
1"
#281000
b11100 &
b10111101 %
b10111101 '
#285000
0"
#290000
b10011001 !
b10011001 (
b10011001 *
b11110000001101 +
b11101101010000 ,
b10111101 -
b11100 )
1"
#291000
b11101 &
b101101 %
b101101 '
#295000
0"
#300000
b10011010 !
b10011010 (
b10011010 *
b11110000111010 +
b11101 )
b101101 -
b11110000001101 ,
1"
#301000
b11110 &
b1001100101 %
b1001100101 '
#305000
0"
#310000
b10100000 !
b10100000 (
b10100000 *
b11111010011111 +
b11110000111010 ,
b1001100101 -
b11110 )
1"
#311000
b11111 &
b1001100011 %
b1001100011 '
#315000
0"
#320000
b10100110 !
b10100110 (
b10100110 *
b100000100000010 +
b11111 )
b1001100011 -
b11111010011111 ,
1"
#321000
b100000 &
b1100001010 %
b1100001010 '
#325000
0"
#330000
b10101110 !
b10101110 (
b10101110 *
b100010000001100 +
b100000100000010 ,
b1100001010 -
b100000 )
1"
#331000
b100001 &
b1010000000 %
b1010000000 '
#335000
0"
#340000
b10110100 !
b10110100 (
b10110100 *
b100011010001100 +
b100001 )
b1010000000 -
b100010000001100 ,
1"
#341000
b100010 &
b100100000 %
b100100000 '
#345000
0"
#350000
b10110111 !
b10110111 (
b10110111 *
b100011110101100 +
b100011010001100 ,
b100100000 -
b100010 )
1"
#351000
b100011 &
b110101010 %
b110101010 '
#355000
0"
#360000
b10111011 !
b10111011 (
b10111011 *
b100100101010110 +
b100011 )
b110101010 -
b100011110101100 ,
1"
#361000
b100100 &
b10011101 %
b10011101 '
#365000
0"
#370000
b10111101 !
b10111101 (
b10111101 *
b100100111110011 +
b100100101010110 ,
b10011101 -
b100100 )
1"
#371000
b100101 &
b1010010110 %
b1010010110 '
#375000
0"
#380000
b11000011 !
b11000011 (
b11000011 *
b100110010001001 +
b100101 )
b1010010110 -
b100100111110011 ,
1"
#381000
b100110 &
b10011 %
b10011 '
#385000
0"
#390000
b11000100 !
b11000100 (
b11000100 *
b100110010011100 +
b100110010001001 ,
b10011 -
b100110 )
1"
#391000
b100111 &
b1101 %
b1101 '
#395000
0"
#400000
b100110010101001 +
b100111 )
b1101 -
b100110010011100 ,
1"
#401000
b101000 &
b1001010011 %
b1001010011 '
#405000
0"
#410000
b11001010 !
b11001010 (
b11001010 *
b100111011111100 +
b100110010101001 ,
b1001010011 -
b101000 )
1"
#411000
b101001 &
b101101011 %
b101101011 '
#415000
0"
#420000
b11001101 !
b11001101 (
b11001101 *
b101000001100111 +
b101001 )
b101101011 -
b100111011111100 ,
1"
#421000
b101010 &
b1011010101 %
b1011010101 '
#425000
0"
#430000
b11010101 !
b11010101 (
b11010101 *
b101001100111100 +
b101000001100111 ,
b1011010101 -
b101010 )
1"
#431000
b101011 &
b1000000010 %
b1000000010 '
#435000
0"
#440000
b11011010 !
b11011010 (
b11011010 *
b101010100111110 +
b101011 )
b1000000010 -
b101001100111100 ,
1"
#441000
b101100 &
b1010101110 %
b1010101110 '
#445000
0"
#450000
b11100001 !
b11100001 (
b11100001 *
b101011111101100 +
b101010100111110 ,
b1010101110 -
b101100 )
1"
#451000
b101101 &
b100011101 %
b100011101 '
#455000
0"
#460000
b11100011 !
b11100011 (
b11100011 *
b101100100001001 +
b101101 )
b100011101 -
b101011111101100 ,
1"
#461000
b101110 &
b1011001111 %
b1011001111 '
#465000
0"
#470000
b11101011 !
b11101011 (
b11101011 *
b101101111011000 +
b101100100001001 ,
b1011001111 -
b101110 )
1"
#471000
b101111 &
b100100011 %
b100100011 '
#475000
0"
#480000
b11101110 !
b11101110 (
b11101110 *
b101110011111011 +
b101111 )
b100100011 -
b101101111011000 ,
1"
#481000
b110000 &
b100001010 %
b100001010 '
#485000
0"
#490000
b11110000 !
b11110000 (
b11110000 *
b101111000000101 +
b101110011111011 ,
b100001010 -
b110000 )
1"
#491000
b110001 &
b1011001010 %
b1011001010 '
#495000
0"
#500000
b11110111 !
b11110111 (
b11110111 *
b110000011001111 +
b110001 )
b1011001010 -
b101111000000101 ,
1"
#501000
b110010 &
b111100 %
b111100 '
#505000
0"
#510000
b11111000 !
b11111000 (
b11111000 *
b110000100001011 +
b110000011001111 ,
b111100 -
b110010 )
1"
#511000
b110011 &
b111110010 %
b111110010 '
#515000
0"
#520000
b11111101 !
b11111101 (
b11111101 *
b110001011111101 +
b110011 )
b111110010 -
b110000100001011 ,
1"
#521000
b110100 &
b110001010 %
b110001010 '
#525000
0"
#530000
b100000001 !
b100000001 (
b100000001 *
b110010010000111 +
b110001011111101 ,
b110001010 -
b110100 )
1"
#531000
b110101 &
b1101000001 %
b1101000001 '
#535000
0"
#540000
b100001001 !
b100001001 (
b100001001 *
b110011111001000 +
b110101 )
b1101000001 -
b110010010000111 ,
1"
#541000
b110110 &
b11011000 %
b11011000 '
#545000
0"
#550000
b100001011 !
b100001011 (
b100001011 *
b110100010100000 +
b110011111001000 ,
b11011000 -
b110110 )
1"
#551000
b110111 &
b1101111000 %
b1101111000 '
#555000
0"
#560000
b100010100 !
b100010100 (
b100010100 *
b110110000011000 +
b110111 )
b1101111000 -
b110100010100000 ,
1"
#561000
b111000 &
b1010001001 %
b1010001001 '
#565000
0"
#570000
b100011011 !
b100011011 (
b100011011 *
b110111010100001 +
b110110000011000 ,
b1010001001 -
b111000 )
1"
#571000
b111001 &
b111101011 %
b111101011 '
#575000
0"
#580000
b100100000 !
b100100000 (
b100100000 *
b111000010001100 +
b111001 )
b111101011 -
b110111010100001 ,
1"
#581000
b111010 &
b110110110 %
b110110110 '
#585000
0"
#590000
b100100100 !
b100100100 (
b100100100 *
b111001001000010 +
b111000010001100 ,
b110110110 -
b111010 )
1"
#591000
b111011 &
b111000110 %
b111000110 '
#595000
0"
#600000
b100101001 !
b100101001 (
b100101001 *
b111010000001000 +
b111011 )
b111000110 -
b111001001000010 ,
1"
#601000
b111100 &
b1110101110 %
b1110101110 '
#605000
0"
#610000
b100110010 !
b100110010 (
b100110010 *
b111011110110110 +
b111010000001000 ,
b1110101110 -
b111100 )
1"
#611000
b111101 &
b1010111100 %
b1010111100 '
#615000
0"
#620000
b100111001 !
b100111001 (
b100111001 *
b111101001110010 +
b111101 )
b1010111100 -
b111011110110110 ,
1"
#621000
b111110 &
b100101010 %
b100101010 '
#625000
0"
#630000
b100111100 !
b100111100 (
b100111100 *
b111101110011100 +
b111101001110010 ,
b100101010 -
b111110 )
1"
#631000
b111111 &
b1000001011 %
b1000001011 '
#635000
0"
#640000
b101000001 !
b101000001 (
b101000001 *
b111110110100111 +
b111111 )
b1000001011 -
b111101110011100 ,
1"
#641000
b1000000 &
b1001110001 %
b1001110001 '
#645000
0"
#650000
b101000111 !
b101000111 (
b101000111 *
b1000000000011000 +
b111110110100111 ,
b1001110001 -
b1000000 )
1"
#651000
b1000001 &
b110000101 %
b110000101 '
#655000
0"
#660000
b101001011 !
b101001011 (
b101001011 *
b1000000110011101 +
b1000001 )
b110000101 -
b1000000000011000 ,
1"
#661000
b1000010 &
b101001111 %
b101001111 '
#665000
0"
#670000
b101001111 !
b101001111 (
b101001111 *
b1000001011101100 +
b1000000110011101 ,
b101001111 -
b1000010 )
1"
#671000
b1000011 &
b111011 %
b111011 '
#675000
0"
#680000
b1000001100100111 +
b1000011 )
b111011 -
b1000001011101100 ,
1"
#681000
b1000100 &
b1100111010 %
b1100111010 '
#685000
0"
#690000
b101011000 !
b101011000 (
b101011000 *
b1000011001100001 +
b1000001100100111 ,
b1100111010 -
b1000100 )
1"
#691000
b1000101 &
b1001111110 %
b1001111110 '
#695000
0"
#700000
b101011110 !
b101011110 (
b101011110 *
b1000100011011111 +
b1000101 )
b1001111110 -
b1000011001100001 ,
1"
#701000
b1000110 &
b1100010101 %
b1100010101 '
#705000
0"
#710000
b101100110 !
b101100110 (
b101100110 *
b1000101111110100 +
b1000100011011111 ,
b1100010101 -
b1000110 )
1"
#711000
b1000111 &
b1111110001 %
b1111110001 '
#715000
0"
#720000
b101110000 !
b101110000 (
b101110000 *
b1000111111100101 +
b1000111 )
b1111110001 -
b1000101111110100 ,
1"
#721000
b1001000 &
b1111011001 %
b1111011001 '
#725000
0"
#730000
b101111010 !
b101111010 (
b101111010 *
b1001001110111110 +
b1000111111100101 ,
b1111011001 -
b1001000 )
1"
#731000
b1001001 &
b1101100010 %
b1101100010 '
#735000
0"
#740000
b110000010 !
b110000010 (
b110000010 *
b1001011100100000 +
b1001001 )
b1101100010 -
b1001001110111110 ,
1"
#741000
b1001010 &
b1101001100 %
b1101001100 '
#745000
0"
#750000
b110001011 !
b110001011 (
b110001011 *
b1001101001101100 +
b1001011100100000 ,
b1101001100 -
b1001010 )
1"
#751000
b1001011 &
b110011111 %
b110011111 '
#755000
0"
#760000
b110001111 !
b110001111 (
b110001111 *
b1001110000001011 +
b1001011 )
b110011111 -
b1001101001101100 ,
1"
#761000
b1001100 &
b110001111 %
b110001111 '
#765000
0"
#770000
b110010011 !
b110010011 (
b110010011 *
b1001110110011010 +
b1001110000001011 ,
b110001111 -
b1001100 )
1"
#771000
b1001101 &
b111111000 %
b111111000 '
#775000
0"
#780000
b110011000 !
b110011000 (
b110011000 *
b1001111110010010 +
b1001101 )
b111111000 -
b1001110110011010 ,
1"
#781000
b1001110 &
b10110111 %
b10110111 '
#785000
0"
#790000
b110011010 !
b110011010 (
b110011010 *
b1010000001001001 +
b1001111110010010 ,
b10110111 -
b1001110 )
1"
#791000
b1001111 &
b1010011111 %
b1010011111 '
#795000
0"
#800000
b110100001 !
b110100001 (
b110100001 *
b1010001011101000 +
b1001111 )
b1010011111 -
b1010000001001001 ,
1"
#801000
b1010000 &
b1011100 %
b1011100 '
#805000
0"
#810000
b1010001101000100 +
b1010001011101000 ,
b1011100 -
b1010000 )
1"
#811000
b1010001 &
b1011011 %
b1011011 '
#815000
0"
#820000
b110100010 !
b110100010 (
b110100010 *
b1010001110011111 +
b1010001 )
b1011011 -
b1010001101000100 ,
1"
#821000
b1010010 &
b1110001001 %
b1110001001 '
#825000
0"
#830000
b110101011 !
b110101011 (
b110101011 *
b1010011100101000 +
b1010001110011111 ,
b1110001001 -
b1010010 )
1"
#831000
b1010011 &
b1001001001 %
b1001001001 '
#835000
0"
#840000
b110110001 !
b110110001 (
b110110001 *
b1010100101110001 +
b1010011 )
b1001001001 -
b1010011100101000 ,
1"
#841000
b1010100 &
b1011010000 %
b1011010000 '
#845000
0"
#850000
b110111000 !
b110111000 (
b110111000 *
b1010110001000001 +
b1010100101110001 ,
b1011010000 -
b1010100 )
1"
#851000
b1010101 &
b11010111 %
b11010111 '
#855000
0"
#860000
b110111011 !
b110111011 (
b110111011 *
b1010110100011000 +
b1010101 )
b11010111 -
b1010110001000001 ,
1"
#861000
b1010110 &
b1010001 %
b1010001 '
#865000
0"
#870000
b1010110101101001 +
b1010110100011000 ,
b1010001 -
b1010110 )
1"
#871000
b1010111 &
b1110010110 %
b1110010110 '
#875000
0"
#880000
b111000101 !
b111000101 (
b111000101 *
b1011000011111111 +
b1010111 )
b1110010110 -
b1010110101101001 ,
1"
#881000
b1011000 &
b1100001100 %
b1100001100 '
#885000
0"
#890000
b111001100 !
b111001100 (
b111001100 *
b1011010000001011 +
b1011000011111111 ,
b1100001100 -
b1011000 )
1"
#891000
b1011001 &
b1011000010 %
b1011000010 '
#895000
0"
#900000
b111010011 !
b111010011 (
b111010011 *
b1011011011001101 +
b1011001 )
b1011000010 -
b1011010000001011 ,
1"
#901000
b1011010 &
b111001000 %
b111001000 '
#905000
0"
#910000
b111011000 !
b111011000 (
b111011000 *
b1011100010010101 +
b1011011011001101 ,
b111001000 -
b1011010 )
1"
#911000
b1011011 &
b1001110111 %
b1001110111 '
#915000
0"
#920000
b111011110 !
b111011110 (
b111011110 *
b1011101100001100 +
b1011011 )
b1001110111 -
b1011100010010101 ,
1"
#921000
b1011100 &
b100111101 %
b100111101 '
#925000
0"
#930000
b111100010 !
b111100010 (
b111100010 *
b1011110001001001 +
b1011101100001100 ,
b100111101 -
b1011100 )
1"
#931000
b1011101 &
b1100010010 %
b1100010010 '
#935000
0"
#940000
b111101001 !
b111101001 (
b111101001 *
b1011111101011011 +
b1011101 )
b1100010010 -
b1011110001001001 ,
1"
#941000
b1011110 &
b1111110 %
b1111110 '
#945000
0"
#950000
b111101011 !
b111101011 (
b111101011 *
b1011111111011001 +
b1011111101011011 ,
b1111110 -
b1011110 )
1"
#951000
b1011111 &
b101101101 %
b101101101 '
#955000
0"
#960000
b111101110 !
b111101110 (
b111101110 *
b1100000101000110 +
b1011111 )
b101101101 -
b1011111111011001 ,
1"
#961000
b1100000 &
b1100111001 %
b1100111001 '
#965000
0"
#970000
b111110111 !
b111110111 (
b111110111 *
b1100010001111111 +
b1100000101000110 ,
b1100111001 -
b1100000 )
1"
#971000
b1100001 &
b1100011111 %
b1100011111 '
#975000
0"
#980000
b111111111 !
b111111111 (
b111111111 *
b1100011110011110 +
b1100001 )
b1100011111 -
b1100010001111111 ,
1"
#981000
b1100010 &
b1011010011 %
b1011010011 '
#985000
0"
#990000
b1000000110 !
b1000000110 (
b1000000110 *
b1100101001110001 +
b1100011110011110 ,
b1011010011 -
b1100010 )
1"
#991000
b1100011 &
b1110000101 %
b1110000101 '
#995000
0"
#1000000
b1000001111 !
b1000001111 (
b1000001111 *
b1100110111110110 +
b1100011 )
b1110000101 -
b1100101001110001 ,
1"
#1001000
b1100100 &
b1111000 %
b1111000 '
